hubmap_clt/__init__.py
hubmap_clt/__main__.py
hubmap_clt/clt-help.txt
hubmap_clt-1.1.3.dist-info/LICENSE
hubmap_clt-1.1.3.dist-info/METADATA
hubmap_clt-1.1.3.dist-info/WHEEL
hubmap_clt-1.1.3.dist-info/entry_points.txt
hubmap_clt-1.1.3.dist-info/top_level.txt
hubmap_clt-1.1.3.dist-info/RECORD
