Metadata-Version: 2.1
Name: hubmap-clt
Version: 1.1.3
Summary: A command line interface to download multiple files and directories from Globus file transfer service using a manifest file.
Home-page: UNKNOWN
Author: Hubmap
Author-email: api-developers@hubmapconsortium.org
License: UNKNOWN
Keywords: HuBMAP CLT,python
Platform: UNKNOWN
Classifier: Programming Language :: Python :: 3
Classifier: License :: OSI Approved :: MIT License
Classifier: Operating System :: OS Independent
Requires-Python: >=3.6
Requires-Dist: certifi (>=2021.10.8)
Requires-Dist: charset-normalizer (>=2.0.10)
Requires-Dist: globus-cli (>=3.1.4)
Requires-Dist: idna (>=3.3)
Requires-Dist: requests (>=2.27.1)
Requires-Dist: urllib3 (>=1.26.8)
